traceml/__init__.py
traceml/exceptions.py
traceml/logger.py
traceml/pkg.py
traceml/py.typed
traceml/artifacts/__init__.py
traceml/artifacts/enums.py
traceml/artifacts/schemas.py
traceml/events/__init__.py
traceml/events/paths.py
traceml/events/schemas.py
traceml/integrations/__init__.py
traceml/integrations/fastai.py
traceml/integrations/fastai_v1.py
traceml/integrations/hugging_face.py
traceml/integrations/ignite.py
traceml/integrations/keras.py
traceml/integrations/langchain.py
traceml/integrations/lightgbm.py
traceml/integrations/pytorch_lightning.py
traceml/integrations/scikit.py
traceml/integrations/tensorboard.py
traceml/integrations/tensorflow.py
traceml/integrations/xgboost.py
traceml/logging/__init__.py
traceml/logging/handler.py
traceml/logging/parser.py
traceml/logging/schemas.py
traceml/logging/streamer.py
traceml/processors/__init__.py
traceml/processors/df_processors.py
traceml/processors/errors.py
traceml/processors/gpu_processor.py
traceml/processors/importance_processors.py
traceml/processors/logs_processor.py
traceml/processors/psutil_processor.py
traceml/processors/events_processors/__init__.py
traceml/processors/events_processors/events_artifacts_processors.py
traceml/processors/events_processors/events_audio_processors.py
traceml/processors/events_processors/events_charts_processors.py
traceml/processors/events_processors/events_image_processors.py
traceml/processors/events_processors/events_metrics_processors.py
traceml/processors/events_processors/events_models_processors.py
traceml/processors/events_processors/events_tables_processors.py
traceml/processors/events_processors/events_video_processors.py
traceml/serialization/__init__.py
traceml/serialization/base.py
traceml/serialization/writer.py
traceml/summary/__init__.py
traceml/summary/df.py
traceml/tracking/__init__.py
traceml/tracking/run.py
traceml/vendor/__init__.py
traceml/vendor/pynvml.py
traceml/vendor/matplotlylib/__init__.py
traceml/vendor/matplotlylib/mpltools.py
traceml-1.2.3.dist-info/licenses/LICENSE
traceml-1.2.3.dist-info/METADATA
traceml-1.2.3.dist-info/WHEEL
traceml-1.2.3.dist-info/top_level.txt
traceml-1.2.3.dist-info/RECORD
