Metadata-Version: 2.4
Name: traceml
Version: 1.2.3
Summary: Engine for ML/Data tracking, visualization, dashboards, and model UI for Polyaxon.
Home-page: https://github.com/polyaxon/traceml
Author: Polyaxon, Inc.
Author-email: contact@polyaxon.com
Maintainer: Polyaxon, Inc.
Maintainer-email: contact@polyaxon.com
License: Apache 2.0
Keywords: polyaxon,aws,s3,microsoft,azure,google cloud storage,gcs,deep-learning,machine-learning,data-science,neural-networks,artificial-intelligence,ai,reinforcement-learning,kubernetes,aws,microsoft,azure,google cloud,tensorFlow,pytorch,matplotlib,plotly,visualization,analytics
Platform: any
Classifier: Intended Audience :: Information Technology
Classifier: Intended Audience :: System Administrators
Classifier: Intended Audience :: Developers
Classifier: Intended Audience :: Science/Research
Classifier: Operating System :: OS Independent
Classifier: Programming Language :: Python :: 3
Classifier: Programming Language :: Python
Classifier: Topic :: Software Development :: Libraries :: Application Frameworks
Classifier: Topic :: Software Development :: Libraries :: Python Modules
Classifier: Topic :: Software Development :: Libraries
Classifier: Topic :: Software Development
Classifier: Topic :: Scientific/Engineering :: Artificial Intelligence
Classifier: Typing :: Typed
Classifier: Programming Language :: Python :: 3 :: Only
Classifier: Programming Language :: Python :: 3.6
Classifier: Programming Language :: Python :: 3.7
Classifier: Programming Language :: Python :: 3.8
Classifier: Programming Language :: Python :: 3.9
Classifier: Programming Language :: Python :: 3.10
Classifier: Programming Language :: Python :: 3.11
Requires-Python: >=3.8
License-File: LICENSE
Provides-Extra: polyaxon
Requires-Dist: polyaxon; extra == "polyaxon"
Provides-Extra: dev
Requires-Dist: pandas; extra == "dev"
Requires-Dist: pyarrow; extra == "dev"
Requires-Dist: ipython; extra == "dev"
Requires-Dist: scikit-learn; extra == "dev"
Requires-Dist: altair; extra == "dev"
Requires-Dist: matplotlib; extra == "dev"
Requires-Dist: moviepy==1.0.3; extra == "dev"
Requires-Dist: plotly>=4.6.0; extra == "dev"
Requires-Dist: Pillow; extra == "dev"
Requires-Dist: bokeh; extra == "dev"
Requires-Dist: aiofiles==24.1.0; extra == "dev"
Requires-Dist: imageio<2.28.0; extra == "dev"
Provides-Extra: all
Requires-Dist: scikit-learn; extra == "all"
Requires-Dist: Pillow; extra == "all"
Requires-Dist: matplotlib; extra == "all"
Requires-Dist: moviepy; extra == "all"
Requires-Dist: plotly; extra == "all"
Requires-Dist: bokeh; extra == "all"
Requires-Dist: pandas; extra == "all"
Requires-Dist: altair; extra == "all"
Dynamic: author
Dynamic: author-email
Dynamic: classifier
Dynamic: description
Dynamic: description-content-type
Dynamic: home-page
Dynamic: keywords
Dynamic: license
Dynamic: license-file
Dynamic: maintainer
Dynamic: maintainer-email
Dynamic: platform
Dynamic: provides-extra
Dynamic: requires-python
Dynamic: summary
